LICENSE
MANIFEST.in
README.rst
setup.cfg
setup.py
datatypes/__init__.py
datatypes/datatypes.py
datatypes/datatypes/LICENSE
datatypes/datatypes/README.md
datatypes/datatypes/datatypes.csv
datatypes/datatypes/values/currencies.csv
datatypes/datatypes/values/genders.csv
datatypes/datatypes/values/marital_statuses.csv
datatypes/datatypes/values/road_types.csv
datatypes/datatypes/values/periods/months.csv
datatypes/datatypes/values/periods/quarters.csv
datatypes/datatypes/values/periods/academic-terms/semesters.csv
datatypes/datatypes/values/regions/eu.csv
datatypes/datatypes/values/regions/sweden/counties.csv
datatypes/datatypes/values/regions/sweden/municipalities.csv
statscraper_datatypes_python.egg-info/PKG-INFO
statscraper_datatypes_python.egg-info/SOURCES.txt
statscraper_datatypes_python.egg-info/dependency_links.txt
statscraper_datatypes_python.egg-info/top_level.txt
test/test.py