Metadata-Version: 1.2
Name: statscraper-datatypes-python
Version: 1.0.0.dev2
Summary: Python bindings for statscraper-datatypes
Home-page: https://gitlab.com/jplusplus/statscraper-datatypes-python
Author: Leonard Wallentin, J++ Stockholm
Author-email: stockholm@jplusplus.org
License: MIT
Platform: UNKNOWN
Requires-Python: >=3.7
